cli/__init__.py
cli/main.py
readability/__init__.py
readability/models.py
readability/parser.py
readability/regexps.py
readability/utils.py
readability_python-0.5.0.dist-info/LICENSE
readability_python-0.5.0.dist-info/METADATA
readability_python-0.5.0.dist-info/WHEEL
readability_python-0.5.0.dist-info/entry_points.txt
readability_python-0.5.0.dist-info/RECORD
