Metadata-Version: 2.3
Name: readability-python
Version: 0.5.0
Summary: Python port of the go-readability library for extracting the main content from web pages
License: Apache 2.0
Keywords: readability,html,content-extraction,web-scraping,mozilla
Author: Eddie Pick
Author-email: eddie@pick.fr
Requires-Python: >=3.8,<4.0
Classifier: Development Status :: 4 - Beta
Classifier: Intended Audience :: Developers
Classifier: License :: OSI Approved :: MIT License
Classifier: License :: Other/Proprietary License
Classifier: Programming Language :: Python :: 3
Classifier: Programming Language :: Python :: 3.8
Classifier: Programming Language :: Python :: 3.9
Classifier: Programming Language :: Python :: 3.10
Classifier: Programming Language :: Python :: 3.11
Classifier: Programming Language :: Python :: 3.12
Classifier: Programming Language :: Python :: 3.13
Classifier: Topic :: Internet :: WWW/HTTP
Classifier: Topic :: Software Development :: Libraries :: Python Modules
Classifier: Topic :: Text Processing :: Markup :: HTML
Requires-Dist: beautifulsoup4 (>=4.12.0,<5.0.0)
Requires-Dist: lxml (>=4.9.0,<5.0.0)
Requires-Dist: python-dateutil (>=2.8.2,<3.0.0)
Requires-Dist: requests (>=2.28.0,<3.0.0)
Project-URL: Documentation, https://github.com/CyranoB/readability-python/blob/main/README.md
Project-URL: Homepage, https://github.com/CyranoB/readability-python/
Project-URL: Repository, https://github.com/CyranoB/readability-python/
